{
  "_class": "shapePath",
  "booleanOperation": -1,
  "do_objectID": "AB2EA296-D84F-4FD3-A0A5-68173DBAF483",
  "edited": true,
  "exportOptions": {
    "_class": "exportOptions",
    "exportFormats": [
    ],
    "includedLayerIds": [
    ],
    "layerOptions": 0,
    "shouldTrim": false
  },
  "frame": {
    "_class": "rect",
    "constrainProportions": false,
    "height": 2.000000000000008,
    "width": 954.0000000000001,
    "x": 5.684341886080801e-14,
    "y": 7.105427357601005e-15
  },
  "isFlippedHorizontal": false,
  "isFlippedVertical": false,
  "isLocked": false,
  "isVisible": true,
  "layerListExpandedType": 0,
  "name": "Path",
  "nameIsFixed": false,
  "path": {
    "_class": "path",
    "isClosed": false,
    "pointRadiusBehaviour": 1,
    "points": [
      {
        "_class": "curvePoint",
        "cornerRadius": 0,
        "curveFrom": "{0.0047169811320754733, 0.74999999999994427}",
        "curveMode": 1,
        "curveTo": "{0.0047169811320754733, 0.74999999999994427}",
        "hasCurveFrom": false,
        "hasCurveTo": false,
        "point": "{0, 0.49999999999999795}"
      },
      {
        "_class": "curvePoint",
        "cornerRadius": 0,
        "curveFrom": "{0.0057651991614255773, 1.2499999999999423}",
        "curveMode": 1,
        "curveTo": "{0.0057651991614255773, 1.2499999999999423}",
        "hasCurveFrom": false,
        "hasCurveTo": false,
        "point": "{1, 0.500000000000002}"
      }
    ]
  },
  "resizingConstraint": 63,
  "resizingType": 0,
  "rotation": 0,
  "shouldBreakMaskChain": false
}