{
  "_class": "shapeGroup",
  "clippingMaskMode": 0,
  "do_objectID": "534A8F29-5E13-43D5-8516-900E01E520BF",
  "exportOptions": {
    "_class": "exportOptions",
    "exportFormats": [
    ],
    "includedLayerIds": [
    ],
    "layerOptions": 0,
    "shouldTrim": false
  },
  "frame": {
    "_class": "rect",
    "constrainProportions": false,
    "height": 13.41,
    "width": 17.59,
    "x": 3.409999999999854,
    "y": 5.590000000000146
  },
  "hasClickThrough": false,
  "hasClippingMask": false,
  "isFlippedHorizontal": false,
  "isFlippedVertical": false,
  "isLocked": false,
  "isVisible": true,
  "layerListExpandedType": 1,
  "layers": [
    {
      "class": "shapePath",
      "id": "3D2CC6DD-D05D-4348-9781-99019A7EBB44"
    }
  ],
  "name": "Shape",
  "nameIsFixed": false,
  "resizingConstraint": 63,
  "resizingType": 0,
  "rotation": 0,
  "shouldBreakMaskChain": false,
  "style": {
    "sharedObjectID": "3BBAF465-BBEC-496B-BB5D-5CBCB0D92A5E"
  },
  "windingRule": 1
}