{
  "_class": "group",
  "do_objectID": "ED747B37-1F08-4677-B841-AF2BC19BF4A1",
  "exportOptions": {
    "_class": "exportOptions",
    "exportFormats": [
    ],
    "includedLayerIds": [
    ],
    "layerOptions": 0,
    "shouldTrim": false
  },
  "frame": {
    "_class": "rect",
    "constrainProportions": false,
    "height": 45,
    "width": 278,
    "x": 278,
    "y": 0
  },
  "hasClickThrough": false,
  "isFlippedHorizontal": false,
  "isFlippedVertical": false,
  "isLocked": false,
  "isVisible": true,
  "layerListExpandedType": 0,
  "layers": [
    {
      "class": "shapeGroup",
      "id": "30E7F033-163A-4470-865F-2D90B6996EA8"
    },
    {
      "class": "text",
      "id": "B2379D89-E590-42A9-AD41-EF411825471C"
    }
  ],
  "name": "Delete Copy 3",
  "nameIsFixed": true,
  "resizingConstraint": 63,
  "resizingType": 0,
  "rotation": 0,
  "shouldBreakMaskChain": false,
  "style": {
    "_class": "style",
    "endDecorationType": 0,
    "miterLimit": 10,
    "startDecorationType": 0
  }
}