{
  "_class": "group",
  "do_objectID": "F90FD766-B615-455E-B90B-048E780BF055",
  "exportOptions": {
    "_class": "exportOptions",
    "exportFormats": [
    ],
    "includedLayerIds": [
    ],
    "layerOptions": 0,
    "shouldTrim": false
  },
  "frame": {
    "_class": "rect",
    "constrainProportions": false,
    "height": 45,
    "width": 100,
    "x": 190,
    "y": 935
  },
  "hasClickThrough": false,
  "isFlippedHorizontal": false,
  "isFlippedVertical": false,
  "isLocked": false,
  "isVisible": true,
  "layerListExpandedType": 0,
  "layers": [
    {
      "class": "shapeGroup",
      "id": "C1FCCC61-64D8-4209-BE81-9D684059BC21"
    },
    {
      "class": "text",
      "id": "E6BF4E41-4EA5-4BD2-B930-306C31B07966"
    }
  ],
  "name": "Delete Copy 2",
  "nameIsFixed": true,
  "resizingConstraint": 63,
  "resizingType": 0,
  "rotation": 0,
  "shouldBreakMaskChain": false,
  "style": {
    "_class": "style",
    "endDecorationType": 0,
    "miterLimit": 10,
    "startDecorationType": 0
  }
}