{
  "_class": "group",
  "do_objectID": "DA7BB766-6F0F-4604-B28C-02E4D536E38B",
  "exportOptions": {
    "_class": "exportOptions",
    "exportFormats": [
    ],
    "includedLayerIds": [
    ],
    "layerOptions": 0,
    "shouldTrim": false
  },
  "frame": {
    "_class": "rect",
    "constrainProportions": false,
    "height": 45,
    "width": 833,
    "x": 96,
    "y": 961
  },
  "hasClickThrough": false,
  "isFlippedHorizontal": false,
  "isFlippedVertical": false,
  "isLocked": false,
  "isVisible": true,
  "layerListExpandedType": 2,
  "layers": [
    {
      "class": "group",
      "id": "229DE103-A3A4-488D-9F13-99BCC863115C"
    },
    {
      "class": "group",
      "id": "D4A77967-5C31-49EC-86BC-9019A92B5068"
    },
    {
      "class": "group",
      "id": "188DCBE7-AA35-4B78-AF71-3B39E3251E3D"
    }
  ],
  "name": "No_Yes_NA Buttons Copy 3",
  "nameIsFixed": true,
  "resizingConstraint": 63,
  "resizingType": 0,
  "rotation": 0,
  "shouldBreakMaskChain": false,
  "style": {
    "_class": "style",
    "endDecorationType": 0,
    "miterLimit": 10,
    "startDecorationType": 0
  }
}