{
  "_class": "shapePath",
  "booleanOperation": -1,
  "do_objectID": "2DBD84AE-0CD0-4AD9-8871-384BA595BFBA",
  "edited": true,
  "exportOptions": {
    "_class": "exportOptions",
    "exportFormats": [
    ],
    "includedLayerIds": [
    ],
    "layerOptions": 0,
    "shouldTrim": false
  },
  "frame": {
    "_class": "rect",
    "constrainProportions": false,
    "height": 60,
    "width": 3,
    "x": 0,
    "y": 0
  },
  "isFlippedHorizontal": false,
  "isFlippedVertical": false,
  "isLocked": false,
  "isVisible": true,
  "layerListExpandedType": 0,
  "name": "Path",
  "nameIsFixed": false,
  "path": {
    "_class": "path",
    "isClosed": false,
    "pointRadiusBehaviour": 1,
    "points": [
      {
        "_class": "curvePoint",
        "cornerRadius": 0,
        "curveFrom": "{0.66666666666666663, 3.4694469519536142e-18}",
        "curveMode": 1,
        "curveTo": "{0.66666666666666663, 3.4694469519536142e-18}",
        "hasCurveFrom": false,
        "hasCurveTo": false,
        "point": "{0.50000000000000233, 0.0083333333333333332}"
      },
      {
        "_class": "curvePoint",
        "cornerRadius": 0,
        "curveFrom": "{1, 0.016666666666666673}",
        "curveMode": 1,
        "curveTo": "{1, 0.016666666666666673}",
        "hasCurveFrom": false,
        "hasCurveTo": false,
        "point": "{0.50000000000000122, 0.99166666666666659}"
      }
    ]
  },
  "resizingConstraint": 63,
  "resizingType": 0,
  "rotation": 0,
  "shouldBreakMaskChain": false
}