{
  "_class": "group",
  "do_objectID": "ED8B15FC-E3B8-4F4B-8FB3-75C957F249D8",
  "exportOptions": {
    "_class": "exportOptions",
    "exportFormats": [
    ],
    "includedLayerIds": [
    ],
    "layerOptions": 0,
    "shouldTrim": false
  },
  "frame": {
    "_class": "rect",
    "constrainProportions": false,
    "height": 39,
    "width": 834,
    "x": 95,
    "y": 530
  },
  "hasClickThrough": false,
  "isFlippedHorizontal": false,
  "isFlippedVertical": false,
  "isLocked": false,
  "isVisible": true,
  "layerListExpandedType": 2,
  "layers": [
    {
      "class": "shapeGroup",
      "id": "01765B2B-C470-4E99-BD5E-5A044CE8EF21"
    },
    {
      "class": "text",
      "id": "8C11B55A-600B-4FD2-A15F-E72BB97F3396"
    }
  ],
  "name": "Group Copy 4",
  "nameIsFixed": false,
  "resizingConstraint": 63,
  "resizingType": 0,
  "rotation": 0,
  "shouldBreakMaskChain": false,
  "style": {
    "_class": "style",
    "endDecorationType": 0,
    "miterLimit": 10,
    "startDecorationType": 0
  }
}